tzst/__init__.py
tzst/__main__.py
tzst/cli.py
tzst/core.py
tzst/exceptions.py
tzst-22.dist-info/METADATA
tzst-22.dist-info/WHEEL
tzst-22.dist-info/entry_points.txt
tzst-22.dist-info/licenses/LICENSE
tzst-22.dist-info/RECORD
