Metadata-Version: 2.4
Name: tzst
Version: 22
Summary: A Python library for creating and manipulating .tzst/.tar.zst archives
Project-URL: Homepage, https://github.com/xixu-me/tzst
Project-URL: Documentation, https://github.com/xixu-me/tzst#readme
Project-URL: Repository, https://github.com/xixu-me/tzst.git
Project-URL: Bug Tracker, https://github.com/xixu-me/tzst/issues
Author: tzst contributors
License-Expression: BSD-3-Clause
License-File: LICENSE
Keywords: archive,compression,tar,zstandard
Classifier: Development Status :: 4 - Beta
Classifier: Intended Audience :: Developers
Classifier: License :: OSI Approved :: BSD License
Classifier: Operating System :: OS Independent
Classifier: Programming Language :: Python :: 3
Classifier: Programming Language :: Python :: 3.8
Classifier: Programming Language :: Python :: 3.9
Classifier: Programming Language :: Python :: 3.10
Classifier: Programming Language :: Python :: 3.11
Classifier: Programming Language :: Python :: 3.12
Classifier: Topic :: Software Development :: Libraries :: Python Modules
Classifier: Topic :: System :: Archiving :: Compression
Requires-Python: >=3.8
Requires-Dist: zstandard<1.0.0,>=0.19.0
Provides-Extra: dev
Requires-Dist: black>=23.0.0; extra == 'dev'
Requires-Dist: pytest-cov>=4.0.0; extra == 'dev'
Requires-Dist: pytest>=7.0.0; extra == 'dev'
Requires-Dist: ruff>=0.1.0; extra == 'dev'
